conananas/__init__.py
conananas/__main__.py
conananas/ananas.py
conananas/application.py
conananas/model/__init__.py
conananas/model/controller.py
conananas/model/model_base.py
conananas/model/names_model.py
conananas/model/package_model.py
conananas/model/packages_model.py
conananas/model/revisions_model.py
conananas/model/versions_model.py
conananas/widgets/__init__.py
conananas/widgets/widget.py
conananas/widgets/ui/__init__.py
conananas/widgets/ui/widget_ui.py
conananas-0.1.0.dist-info/licenses/LICENSE
conananas-0.1.0.dist-info/METADATA
conananas-0.1.0.dist-info/WHEEL
conananas-0.1.0.dist-info/top_level.txt
conananas-0.1.0.dist-info/RECORD
