Metadata-Version: 2.4
Name: conananas
Version: 0.1.0
Summary: An ananas for conan
Home-page: https://github.com/philippun1/conananas
Author: Philipp Unger
Author-email: philipp.unger.1988@gmail.com
License: MIT
License-File: LICENSE
Requires-Dist: PySide6<6.9,>=6.8
Requires-Dist: conan<3,>=2
Dynamic: author
Dynamic: author-email
Dynamic: home-page
Dynamic: license
Dynamic: license-file
Dynamic: requires-dist
Dynamic: summary
